camelcart/__init__.py
camelcart/hello.py
camelcart-0.0.1.dist-info/LICENSE
camelcart-0.0.1.dist-info/METADATA
camelcart-0.0.1.dist-info/WHEEL
camelcart-0.0.1.dist-info/top_level.txt
camelcart-0.0.1.dist-info/RECORD
